cookieman/__init__.py
cookieman/compat.py
cookieman/cookie.py
cookieman/exceptions.py
cookieman/limits.py
cookieman/serializer.py
cookieman/session.py
cookieman/resources/__init__.py
cookieman/resources/__init__.pyc
cookieman/resources/limits.ini
cookieman/tests/__init__.py
cookieman/tests/cookie.py
cookieman/tests/limits.py
cookieman/tests/meta.py
cookieman/tests/test_code.py
cookieman/tests/test_cookie.py
cookieman/tests/test_integration.py
cookieman/tests/test_limits.py
cookieman-0.0.3.dist-info/LICENSE
cookieman-0.0.3.dist-info/METADATA
cookieman-0.0.3.dist-info/WHEEL
cookieman-0.0.3.dist-info/top_level.txt
cookieman-0.0.3.dist-info/zip-safe
cookieman-0.0.3.dist-info/RECORD
