Metadata-Version: 2.1
Name: cookieman
Version: 0.0.3
Summary: Browser-aware multi-cookie flask session
Home-page: https://gitlab.com/ergoithz/cookieman
Author: Felipe A. Hernandez
Author-email: ergoithz@gmail.com
License: MIT
Keywords: web,browser
Platform: any
Classifier: Development Status :: 4 - Beta
Classifier: License :: OSI Approved :: MIT License
Classifier: Operating System :: OS Independent
Classifier: Programming Language :: Python :: 3
Classifier: Framework :: Flask
Requires-Dist: six
Requires-Dist: msgpack
Requires-Dist: itsdangerous
Requires-Dist: werkzeug
Requires-Dist: flask
Requires-Dist: importlib-resources ; python_version < "3.7"
